azure/mgmt/billingbenefits/__init__.py
azure/mgmt/billingbenefits/_billing_benefits_rp.py
azure/mgmt/billingbenefits/_configuration.py
azure/mgmt/billingbenefits/_patch.py
azure/mgmt/billingbenefits/_serialization.py
azure/mgmt/billingbenefits/_vendor.py
azure/mgmt/billingbenefits/_version.py
azure/mgmt/billingbenefits/py.typed
azure/mgmt/billingbenefits/aio/__init__.py
azure/mgmt/billingbenefits/aio/_billing_benefits_rp.py
azure/mgmt/billingbenefits/aio/_configuration.py
azure/mgmt/billingbenefits/aio/_patch.py
azure/mgmt/billingbenefits/aio/_vendor.py
azure/mgmt/billingbenefits/aio/operations/__init__.py
azure/mgmt/billingbenefits/aio/operations/_billing_benefits_rp_operations.py
azure/mgmt/billingbenefits/aio/operations/_operations.py
azure/mgmt/billingbenefits/aio/operations/_patch.py
azure/mgmt/billingbenefits/aio/operations/_reservation_order_alias_operations.py
azure/mgmt/billingbenefits/aio/operations/_savings_plan_operations.py
azure/mgmt/billingbenefits/aio/operations/_savings_plan_order_alias_operations.py
azure/mgmt/billingbenefits/aio/operations/_savings_plan_order_operations.py
azure/mgmt/billingbenefits/models/__init__.py
azure/mgmt/billingbenefits/models/_billing_benefits_rp_enums.py
azure/mgmt/billingbenefits/models/_models_py3.py
azure/mgmt/billingbenefits/models/_patch.py
azure/mgmt/billingbenefits/operations/__init__.py
azure/mgmt/billingbenefits/operations/_billing_benefits_rp_operations.py
azure/mgmt/billingbenefits/operations/_operations.py
azure/mgmt/billingbenefits/operations/_patch.py
azure/mgmt/billingbenefits/operations/_reservation_order_alias_operations.py
azure/mgmt/billingbenefits/operations/_savings_plan_operations.py
azure/mgmt/billingbenefits/operations/_savings_plan_order_alias_operations.py
azure/mgmt/billingbenefits/operations/_savings_plan_order_operations.py
azure_mgmt_billingbenefits-1.0.0b1.dist-info/LICENSE
azure_mgmt_billingbenefits-1.0.0b1.dist-info/METADATA
azure_mgmt_billingbenefits-1.0.0b1.dist-info/WHEEL
azure_mgmt_billingbenefits-1.0.0b1.dist-info/top_level.txt
azure_mgmt_billingbenefits-1.0.0b1.dist-info/RECORD
